meetcap/__init__.py
meetcap/cli.py
meetcap/core/__init__.py
meetcap/core/devices.py
meetcap/core/hotkeys.py
meetcap/core/recorder.py
meetcap/services/__init__.py
meetcap/services/model_download.py
meetcap/services/summarization.py
meetcap/services/transcription.py
meetcap/utils/__init__.py
meetcap/utils/config.py
meetcap/utils/logger.py
meetcap/utils/memory.py
meetcap-1.3.1.dist-info/METADATA
meetcap-1.3.1.dist-info/WHEEL
meetcap-1.3.1.dist-info/entry_points.txt
meetcap-1.3.1.dist-info/RECORD
