Metadata-Version: 2.4
Name: meetcap
Version: 1.3.1
Summary: Offline meeting recorder & summarizer for macOS
Author-email: Juan <juanqui@villafam.com>
License-Expression: MIT
Keywords: macos,meeting,recorder,summarization,transcription
Classifier: Development Status :: 4 - Beta
Classifier: Environment :: Console
Classifier: Intended Audience :: End Users/Desktop
Classifier: License :: OSI Approved :: MIT License
Classifier: Operating System :: MacOS
Classifier: Programming Language :: Python :: 3
Classifier: Programming Language :: Python :: 3.10
Classifier: Programming Language :: Python :: 3.11
Classifier: Programming Language :: Python :: 3.12
Classifier: Topic :: Multimedia :: Sound/Audio :: Capture/Recording
Requires-Python: >=3.10
Requires-Dist: llama-cpp-python>=0.3.15
Requires-Dist: psutil>=6.1.0
Requires-Dist: pynput>=1.8.1
Requires-Dist: rich>=14.1.0
Requires-Dist: toml>=0.10.2
Requires-Dist: tomli>=2.2.1; python_version < '3.11'
Requires-Dist: typer>=0.16.0
Requires-Dist: urllib3>=2.5.0
Provides-Extra: dev
Requires-Dist: black>=25.1.0; extra == 'dev'
Requires-Dist: bump2version>=1.0.1; extra == 'dev'
Requires-Dist: coverage[toml]>=7.6.9; extra == 'dev'
Requires-Dist: mypy>=1.13.0; extra == 'dev'
Requires-Dist: pytest-asyncio>=0.25.0; extra == 'dev'
Requires-Dist: pytest-cov>=6.2.1; extra == 'dev'
Requires-Dist: pytest-mock>=3.14.0; extra == 'dev'
Requires-Dist: pytest-timeout>=2.4.0; extra == 'dev'
Requires-Dist: pytest>=8.4.1; extra == 'dev'
Requires-Dist: ruff>=0.12.8; extra == 'dev'
Provides-Extra: mlx-stt
Requires-Dist: mlx-whisper>=0.4.2; extra == 'mlx-stt'
Provides-Extra: stt
Requires-Dist: faster-whisper>=1.2.0; extra == 'stt'
Provides-Extra: vosk-stt
Requires-Dist: scikit-learn>=1.3.0; extra == 'vosk-stt'
Requires-Dist: soundfile>=0.13.1; extra == 'vosk-stt'
Requires-Dist: vosk>=0.3.44; extra == 'vosk-stt'
